azmq/__init__.py
azmq/common.py
azmq/constants.py
azmq/containers.py
azmq/context.py
azmq/crypto.py
azmq/errors.py
azmq/log.py
azmq/metadata.py
azmq/multiplexer.py
azmq/socket.py
azmq/zap.py
azmq/connections/__init__.py
azmq/connections/base.py
azmq/connections/inproc.py
azmq/connections/stream.py
azmq/engines/__init__.py
azmq/engines/base.py
azmq/engines/inproc.py
azmq/engines/ipc.py
azmq/engines/tcp.py
azmq/engines/win32.py
azmq/mechanisms/__init__.py
azmq/mechanisms/base.py
azmq/mechanisms/curve_client.py
azmq/mechanisms/curve_server.py
azmq/mechanisms/null.py
azmq/mechanisms/plain_client.py
azmq/mechanisms/plain_server.py
azmq/transports/__init__.py
azmq/transports/inproc.py
azmq-1.0.6.dist-info/DESCRIPTION.rst
azmq-1.0.6.dist-info/METADATA
azmq-1.0.6.dist-info/RECORD
azmq-1.0.6.dist-info/WHEEL
azmq-1.0.6.dist-info/metadata.json
azmq-1.0.6.dist-info/top_level.txt
tests/integration/__init__.py
tests/integration/test_interoperability.py
tests/integration/test_scenarios.py
tests/integration/test_security.py
tests/unit/__init__.py
tests/unit/test_common.py
tests/unit/test_containers.py
tests/unit/test_context.py
tests/unit/test_metadata.py
tests/unit/test_multiplexer.py
tests/unit/test_socket.py
tests/unit/test_zap.py
tests/unit/test_connections/__init__.py
tests/unit/test_connections/test_base.py
tests/unit/test_connections/test_stream.py
tests/unit/test_mechanisms/__init__.py
tests/unit/test_mechanisms/test_base.py
tests/unit/test_mechanisms/test_curve_client.py
tests/unit/test_mechanisms/test_curve_server.py
